pygeoif/__init__.py
pygeoif/about.py
pygeoif/exceptions.py
pygeoif/factories.py
pygeoif/feature.py
pygeoif/functions.py
pygeoif/geometry.py
pygeoif/py.typed
pygeoif/types.py
pygeoif/hypothesis/__init__.py
pygeoif/hypothesis/strategies.py
pygeoif-1.5.0.dist-info/METADATA
pygeoif-1.5.0.dist-info/WHEEL
pygeoif-1.5.0.dist-info/top_level.txt
pygeoif-1.5.0.dist-info/RECORD
